setup.py
nupic_studio/__init__.py
nupic_studio/nupic_studio.config
nupic_studio/program.py
nupic_studio/project.py
nupic_studio.egg-info/PKG-INFO
nupic_studio.egg-info/SOURCES.txt
nupic_studio.egg-info/dependency_links.txt
nupic_studio.egg-info/entry_points.txt
nupic_studio.egg-info/requires.txt
nupic_studio.egg-info/top_level.txt
nupic_studio/htm/__init__.py
nupic_studio/htm/bit.py
nupic_studio/htm/cell.py
nupic_studio/htm/column.py
nupic_studio/htm/encoding.py
nupic_studio/htm/link.py
nupic_studio/htm/network.py
nupic_studio/htm/node.py
nupic_studio/htm/node_region.py
nupic_studio/htm/node_sensor.py
nupic_studio/htm/segment.py
nupic_studio/htm/synapse.py
nupic_studio/images/__init__.py
nupic_studio/images/buttonInitializeHTM.png
nupic_studio/images/buttonStepFastHTM.png
nupic_studio/images/buttonStepHTM.png
nupic_studio/images/buttonStopHTM.png
nupic_studio/images/logo.ico
nupic_studio/images/logo.png
nupic_studio/images/splash.png
nupic_studio/images/splash_blank.jpg
nupic_studio/projects/__init__.py
nupic_studio/projects/counting.csv
nupic_studio/projects/counting.nuproj
nupic_studio/projects/hot_gym.csv
nupic_studio/projects/hot_gym.nuproj
nupic_studio/projects/squares.nuproj
nupic_studio/projects/squares_left.csv
nupic_studio/projects/squares_right.csv
nupic_studio/ui/__init__.py
nupic_studio/ui/architecture_form.py
nupic_studio/ui/main_form.py
nupic_studio/ui/node_information_form.py
nupic_studio/ui/node_region_form.py
nupic_studio/ui/node_sensor_encoding_form.py
nupic_studio/ui/node_sensor_form.py
nupic_studio/ui/output_form.py
nupic_studio/ui/project_properties_form.py
nupic_studio/ui/simulation_form.py
nupic_studio/ui/simulation_legend_form.py
nupic_studio/ui/start_form.py