Metadata-Version: 1.1
Name: nupic-studio
Version: 1.1.1
Summary: NuPIC Studio is a virtual studio that allows developers to create, debug, and visualize HTM networks from NuPIC library
Home-page: https://github.com/nupic-community/nupic.studio
Author: David Ragazzi
Author-email: david_ragazzi@hotmail.com
License: UNKNOWN
Platform: UNKNOWN
Classifier: Programming Language :: Python
Classifier: Programming Language :: Python :: 2
Classifier: License :: OSI Approved :: GNU General Public License (GPL)
Classifier: Operating System :: OS Independent
Classifier: Development Status :: 5 - Production/Stable
Classifier: Environment :: Console
Classifier: Intended Audience :: Science/Research
Classifier: Topic :: Scientific/Engineering :: Artificial Intelligence
